AWSomeOverview/AWSomeOverview.py
AWSomeOverview/__init__.py
AWSomeOverview/deplugins/__init__.py
AWSomeOverview/deplugins/ami.py
AWSomeOverview/deplugins/ami_mismatch.py
AWSomeOverview/deplugins/autoscalinggroups.py
AWSomeOverview/deplugins/base.py
AWSomeOverview/deplugins/cformation.py
AWSomeOverview/deplugins/cfront_aliases.py
AWSomeOverview/deplugins/cfront_ssl.py
AWSomeOverview/deplugins/cwatch.py
AWSomeOverview/deplugins/dynamo.py
AWSomeOverview/deplugins/dynamo_keys.py
AWSomeOverview/deplugins/dynamo_streams.py
AWSomeOverview/deplugins/ec2.py
AWSomeOverview/deplugins/elb.py
AWSomeOverview/deplugins/elb_attr.py
AWSomeOverview/deplugins/iam.py
AWSomeOverview/deplugins/id_format.py
AWSomeOverview/deplugins/route53.py
AWSomeOverview/deplugins/s3.py
AWSomeOverview/deplugins/tags.py
AWSomeOverview/deplugins/vpc.py
AWSomeOverview/outputformat/__init__.py
AWSomeOverview/outputformat/base.py
AWSomeOverview/outputformat/console.py
AWSomeOverview/outputformat/wiki.py
AWSomeOverview-1.2.5.dist-info/DESCRIPTION.rst
AWSomeOverview-1.2.5.dist-info/METADATA
AWSomeOverview-1.2.5.dist-info/RECORD
AWSomeOverview-1.2.5.dist-info/WHEEL
AWSomeOverview-1.2.5.dist-info/entry_points.txt
AWSomeOverview-1.2.5.dist-info/metadata.json
AWSomeOverview-1.2.5.dist-info/top_level.txt
