Metadata-Version: 2.0
Name: AWSomeOverview
Version: 1.2.5
Summary: A tool to easily iterate across multiple given AWS accounts, AWS regions and AWS services to aggregate and output facts.
Home-page: UNKNOWN
Author: Arndt Roth
Author-email: arndt.roth@here.com
License: Apache License, Version 2.0
Keywords: aws cli devops fact retrieval comparison
Platform: UNKNOWN
Classifier: Development Status :: 4 - Beta
Classifier: Environment :: Console
Classifier: Intended Audience :: Developers
Classifier: Intended Audience :: System Administrators
Classifier: License :: OSI Approved :: Apache Software License
Classifier: Operating System :: MacOS :: MacOS X
Classifier: Operating System :: POSIX
Classifier: Operating System :: Unix
Classifier: Programming Language :: Python :: 3
Classifier: Programming Language :: Python :: 3.1
Classifier: Programming Language :: Python :: 3.2
Classifier: Programming Language :: Python :: 3.3
Classifier: Programming Language :: Python :: 3.4
Classifier: Programming Language :: Python :: 3.5
Classifier: Programming Language :: Python :: 3.6
Classifier: Programming Language :: Python
Classifier: Topic :: System :: Monitoring
Classifier: Topic :: Utilities
Requires-Dist: argparse (>=1.1)
Requires-Dist: boto3 (>=1.3.1)
Requires-Dist: tabulate (>=0.7.2)
